{
    "datetime": "20230913043038811938",
    "content": [
        {
            "title": "Все недостатки мотора 2В-12-3А семейства «Арматы» исправлены инженерами",
            "link": "https://dzen.ru/news/story/Vse_nedostatki_motora_2V-12-3A_semejstva_Armaty_ispravleny_inzhenerami--ba8a52aa89a5a09ae265d69706fbf9ed?lang=ru&rubric=auto&fan=1&stid=pRlK&t=1694568065&persistent_id=2740591261&story=37c09374-4654-5f8c-b8e8-1885b862a1b2&issue_tld=ru",
            "preview": "https://avatars.dzeninfra.ru/get-ynews/114574/bbaf05b66e556b80e3927d9138900a70/366x183",
            "image": "https://avatars.dzeninfra.ru/get-ynews/114574/bbaf05b66e556b80e3927d9138900a70/800x400",
            "subtitles_other": [
                "Все недостатки мотора 2В-12-3А семейства «Арматы» исправлены инженерами",
                "Инженеры устранили все недостатки двигателя «Арматы»"
            ],
            "subtitle": [
                "Улучшенный вариант мотора был представлен в рамках международного форума «Армия-2023».",
                "Турбопоршневой агрегат после последних модернизаций по достоинству считается теперь одним из лучших в семействе «Арматы».",
                "Двенадцатилитровый мотор обеспечивает производительность в пределах 1500 лошадиных сил (фото: t.me/«Танки мира»).",
                "Тем не менее, инженерам удалось устранить чрезмерный расход топлива и масла, обеспечив более экономичные показатели."
            ]
        }
    ]
}