{
    "datetime": "20230913073030302050",
    "content": [
        {
            "title": "Автозавод ЗМЗ завершил выпуск легендарных «легковых» турбодизелей ЗМЗ-514",
            "link": "https://dzen.ru/news/story/Avtozavod_ZMZ_zavershil_vypusk_legendarnykh_legkovykh_turbodizelej_ZMZ-514--a052488dbf028150363b992ea8fce80c?lang=ru&rubric=auto&fan=1&stid=4wYKGSHn24n9wx3MrwF9&t=1694578847&persistent_id=2740575925&story=d2a215a3-7d99-5360-9684-a8a40774132f&issue_tld=ru",
            "preview": "https://avatars.dzeninfra.ru/get-ynews/5520796/dfd9c58d29bb2a15fce28212bca40d85/366x183",
            "image": "https://avatars.dzeninfra.ru/get-ynews/5520796/dfd9c58d29bb2a15fce28212bca40d85/800x400",
            "subtitles_other": [],
            "subtitle": [
                "После ухода из России большинства иностранных автоконцернов дилеры по-разному адаптировались к кризису — некоторые даже получили новые активы.",
                "Как «Авилон» взаимодействует с бывшим офисом Volkswagen в РФ (ныне АГР), который теперь вошел в периметр группы, о стратегиях марок из Китая на фоне ограничений и ситуации на рынке в интервью “Ъ” рассказал глава «Авилона» Александр Никонов.",
                "Продажи автомобилей дают около 70% выручки, aftersales — около 30%.",
                "Далее автомобили продаются владельцами либо владельцы пытаются сэкономить, обращаются в независимые СТО."
            ]
        }
    ]
}